[{"documentName": "atique_ali_0.txt_2022-09-16_06:55:39.1.txt", "document": "MY FOOTPRINT...\n@ (+91) 797-401-6342  atique.ali393@outlook.com\nATIQUE ALI\nData Scientist | Machine Learning Engineer\nOver 5.9 years of successful career spanning in technology services industry\nwith proven record of accomplishments in architecting products with\nPredictive Modelling, Clustering Segmentation, Machine Learning Algorithm,\nMainframe Development, Web Scrapping, Data Analytics & Business\nIntelligence.\nA professional in leading high-performance team & SDLC using Agile\nmethodologies, writing requirements, modelling products & Data visualization.\nPROFESSIONAL EXPERIENCE\nGU\nGs),\nMar 2020\nPRESENT\nJun 2017\nMar 2020\nDATA SCIENTIST (MODULE LEAD)\nSopra Banking Software / Noida, IN\nLed a team of 5-6 developers to deliver the Bank products with\nProduct-Costumer Segmentations using machine learning\nalgorithms\nEvaluated Bank transaction legitimacy using Statistical/ML\nmodels\nBuild Loan approval/acceptance prediction algorithm for\nvarious types of loan and bank products.\nAl model of Customer's Exit from the Bank for specific Bank\nproduct configuration\nEnsured data quality, created stories for team, maintained\ntechnical documents\nCommunicated with team and presented demo to clients on\nBusiness Intelligence tool (Power BI)\nDATA SCIENTIST (PRODUCT DEVELOPER)\nDXC Technology / Noida, IN\nBuild hedging fund algorithm using deep-hedging machine\nlearning model.\nForecasting index rate on the periodic days\nEvaluated risk prediction using machine learning algorithm\nwhile underwriting policies for Life Insurance\nWeb-scrapping to fetch rates for insurance & annuity on daily\nbasis more efficiently from websites.\nModernized Mainframe product, COBOL, RestAPI using\nWebmethod Entirex.\nExperienced working in Business Intelligence Environment\nlike Visualization tool  Power BI\n() https://www.linkedin.com/in/atique-ali/\nSKILLS\n \nok\nok\nok\nPython Scripting\nMachine Learning Techniques\nSQL\nMatplotlib / Power BI\nScikit /Keras/Tensorflow/PyTorch\nNLP / Web Scraping\nClustering/Regression\nClassification/Statistical Inference\nData Mining/Data Analysis/EDA\nIBM Mainframe (Cobol, JCL, DB2)\nADDITIONAL SKILLS\nok\nok\nok\n=\nProduct Management\nProduct Roadmap/Create stories\nStatistics/Mathematics\nAgile & Scrum\nGit, Jira & Cloud (Azure & GCP)\nINTERNSHIP PROJECTS\nDCGANS  Pokmon Faces\nEmployee Turnover Prediction\nBitcoin Prediction\nFraud Detection\nIPL Data Analysis & Prediction\nSales Demand Forecast\nAmazon-Best-Selling-Product\nFace Mask Detection\nSentiment Analysis\nDOMAIN\nok\nok\nInsurance & Annuity\nBanking\nINTERESTS\nok\nok\nok\nMMA workout.\nWatching TV shows like Friends\n& Fresh Prince of Bel Air.\nGoogling.\n", "annotation": [{"start": 263, "end": 283, "label": "SKILLS", "text": "Predictive Modelling", "propertiesList": [], "commentsList": []}, {"start": 285, "end": 308, "label": "SKILLS", "text": "Clustering Segmentation", "propertiesList": [], "commentsList": []}, {"start": 310, "end": 336, "label": "SKILLS", "text": "Machine Learning Algorithm", "propertiesList": [], "commentsList": []}, {"start": 338, "end": 359, "label": "SKILLS", "text": "Mainframe Development", "propertiesList": [], "commentsList": []}, {"start": 361, "end": 374, "label": "SKILLS", "text": "Web Scrapping", "propertiesList": [], "commentsList": []}, {"start": 376, "end": 401, "label": "SKILLS", "text": "Data Analytics & Business", "propertiesList": [], "commentsList": []}, {"start": 585, "end": 587, "label": "SKILLS", "text": "GU", "propertiesList": [], "commentsList": []}, {"start": 588, "end": 592, "label": "SKILLS", "text": "Gs),", "propertiesList": [], "commentsList": []}, {"start": 792, "end": 819, "label": "SKILLS", "text": "machine learning\nalgorithms", "propertiesList": [], "commentsList": []}, {"start": 864, "end": 885, "label": "SKILLS", "text": "Statistical/ML\nmodels", "propertiesList": [], "commentsList": []}, {"start": 906, "end": 937, "label": "SKILLS", "text": "acceptance prediction algorithm", "propertiesList": [], "commentsList": []}, {"start": 1335, "end": 1370, "label": "SKILLS", "text": "deep-hedging machine\nlearning model", "propertiesList": [], "commentsList": []}, {"start": 1372, "end": 1394, "label": "SKILLS", "text": "Forecasting index rate", "propertiesList": [], "commentsList": []}, {"start": 1448, "end": 1474, "label": "SKILLS", "text": "machine learning algorithm", "propertiesList": [], "commentsList": []}, {"start": 1622, "end": 1650, "label": "SKILLS", "text": "Modernized Mainframe product", "propertiesList": [], "commentsList": []}, {"start": 1652, "end": 1657, "label": "SKILLS", "text": "COBOL", "propertiesList": [], "commentsList": []}, {"start": 1659, "end": 1666, "label": "SKILLS", "text": "RestAPI", "propertiesList": [], "commentsList": []}, {"start": 1673, "end": 1690, "label": "SKILLS", "text": "Webmethod Entirex", "propertiesList": [], "commentsList": []}, {"start": 1844, "end": 1860, "label": "SKILLS", "text": "Python Scripting", "propertiesList": [], "commentsList": []}, {"start": 1861, "end": 1888, "label": "SKILLS", "text": "Machine Learning Techniques", "propertiesList": [], "commentsList": []}, {"start": 1889, "end": 1892, "label": "SKILLS", "text": "SQL", "propertiesList": [], "commentsList": []}, {"start": 1893, "end": 1914, "label": "SKILLS", "text": "Matplotlib / Power BI", "propertiesList": [], "commentsList": []}, {"start": 1915, "end": 1921, "label": "SKILLS", "text": "Scikit", "propertiesList": [], "commentsList": []}, {"start": 1922, "end": 1928, "label": "SKILLS", "text": "/Keras", "propertiesList": [], "commentsList": []}, {"start": 1929, "end": 1939, "label": "SKILLS", "text": "Tensorflow", "propertiesList": [], "commentsList": []}, {"start": 1940, "end": 1947, "label": "SKILLS", "text": "PyTorch", "propertiesList": [], "commentsList": []}, {"start": 1948, "end": 1951, "label": "SKILLS", "text": "NLP", "propertiesList": [], "commentsList": []}, {"start": 1954, "end": 1966, "label": "SKILLS", "text": "Web Scraping", "propertiesList": [], "commentsList": []}, {"start": 1967, "end": 1977, "label": "SKILLS", "text": "Clustering", "propertiesList": [], "commentsList": []}, {"start": 1978, "end": 1988, "label": "SKILLS", "text": "Regression", "propertiesList": [], "commentsList": []}, {"start": 1989, "end": 2003, "label": "SKILLS", "text": "Classification", "propertiesList": [], "commentsList": []}, {"start": 2004, "end": 2025, "label": "SKILLS", "text": "Statistical Inference", "propertiesList": [], "commentsList": []}, {"start": 2026, "end": 2037, "label": "SKILLS", "text": "Data Mining", "propertiesList": [], "commentsList": []}, {"start": 2038, "end": 2051, "label": "SKILLS", "text": "Data Analysis", "propertiesList": [], "commentsList": []}, {"start": 2052, "end": 2055, "label": "SKILLS", "text": "EDA", "propertiesList": [], "commentsList": []}, {"start": 2056, "end": 2069, "label": "SKILLS", "text": "IBM Mainframe", "propertiesList": [], "commentsList": []}, {"start": 2071, "end": 2076, "label": "SKILLS", "text": "Cobol", "propertiesList": [], "commentsList": []}, {"start": 2078, "end": 2082, "label": "SKILLS", "text": "JCL,", "propertiesList": [], "commentsList": []}, {"start": 2083, "end": 2086, "label": "SKILLS", "text": "DB2", "propertiesList": [], "commentsList": []}, {"start": 2117, "end": 2135, "label": "SKILLS", "text": "Product Management", "propertiesList": [], "commentsList": []}, {"start": 2136, "end": 2151, "label": "SKILLS", "text": "Product Roadmap", "propertiesList": [], "commentsList": []}, {"start": 2167, "end": 2177, "label": "SKILLS", "text": "Statistics", "propertiesList": [], "commentsList": []}, {"start": 2178, "end": 2189, "label": "SKILLS", "text": "Mathematics", "propertiesList": [], "commentsList": []}, {"start": 2190, "end": 2203, "label": "SKILLS", "text": "Agile & Scrum", "propertiesList": [], "commentsList": []}, {"start": 2204, "end": 2207, "label": "SKILLS", "text": "Git", "propertiesList": [], "commentsList": []}, {"start": 2209, "end": 2213, "label": "SKILLS", "text": "Jira", "propertiesList": [], "commentsList": []}, {"start": 2216, "end": 2221, "label": "SKILLS", "text": "Cloud", "propertiesList": [], "commentsList": []}, {"start": 2223, "end": 2228, "label": "SKILLS", "text": "Azure", "propertiesList": [], "commentsList": []}, {"start": 2231, "end": 2234, "label": "SKILLS", "text": "GCP", "propertiesList": [], "commentsList": []}], "user_input": ""}]